{"dependencies":[{"name":"/Users/Joe/Coding/josephtohdjojo/josephtohdjojo.com/.babelrc","includedInParent":true,"mtime":1518145663000}],"generated":{"js":"\"use strict\";\n\nObject.defineProperty(exports, \"__esModule\", {\n  value: true\n});\nvar tmpl = \"<div class=\\\"about animated fadeIn\\\">\\n  <div class=\\\"about-container\\\">\\n    <div class=\\\"about-left\\\">\\n      <h1>JOSEPH<br>TOH<i>|</i>DJOJO</h1>\\n      <div class=\\\"line\\\"></div>\\n    </div>\\n    <div class=\\\"about-right\\\">\\n      <div class=\\\"ghost\\\"></div>\\n      <div class=\\\"title\\\">\\n        <div class=\\\"line\\\"></div>\\n        <p>WHO I AM</p>\\n        <div class=\\\"line\\\"></div>\\n      </div>\\n      <br>\\n      <p>Hi, I'm Joe! I develop and design thoughtful digital experiences out of <i>Brooklyn, NY</i>. My love for <i>programming</i> stems from the junction of my two hobbies, art and technology. My goal is to solve problems for brands through thoughtful ideas that translate into designs for various mediums. I love to explore different avenues of <i>creativity</i> and build small pieces of software in my spare time.</p>\\n    </div>\\n  </div>\\n</div>\";\n\nexports.default = tmpl;","map":{"mappings":[{"generated":{"line":6,"column":0},"source":"views/about/about-tmpl.js","original":{"line":1,"column":0}},{"name":"tmpl","generated":{"line":6,"column":4},"source":"views/about/about-tmpl.js","original":{"line":1,"column":6}},{"generated":{"line":6,"column":881},"source":"views/about/about-tmpl.js","original":{"line":1,"column":0}},{"name":"tmpl","generated":{"line":8,"column":18},"source":"views/about/about-tmpl.js","original":{"line":20,"column":15}}],"sources":{"views/about/about-tmpl.js":"const tmpl = `<div class=\"about animated fadeIn\">\n  <div class=\"about-container\">\n    <div class=\"about-left\">\n      <h1>JOSEPH<br>TOH<i>|</i>DJOJO</h1>\n      <div class=\"line\"></div>\n    </div>\n    <div class=\"about-right\">\n      <div class=\"ghost\"></div>\n      <div class=\"title\">\n        <div class=\"line\"></div>\n        <p>WHO I AM</p>\n        <div class=\"line\"></div>\n      </div>\n      <br>\n      <p>Hi, I'm Joe! I develop and design thoughtful digital experiences out of <i>Brooklyn, NY</i>. My love for <i>programming</i> stems from the junction of my two hobbies, art and technology. My goal is to solve problems for brands through thoughtful ideas that translate into designs for various mediums. I love to explore different avenues of <i>creativity</i> and build small pieces of software in my spare time.</p>\n    </div>\n  </div>\n</div>`\n\nexport default tmpl\n"},"lineCount":null}},"hash":"0068fee00efb10b7c56cce07fb281a1d","cacheData":{"env":{}}}